{
  "vclaim_id": "vclaim-sno-german-news-trump-nato",
  "vclaim": "A video shows a German newscaster laughing at President Trump's statements at a NATO summit.",
  "title": "Is This How German News Covered President Trump at the NATO Summit?",
  "subtitle": "Years-old footage of a newscaster laughing was repurposed and shared as if it showed a reporter mocking President Trump.",
  "page_url": "https://www.snopes.com/fact-check/german-news-trump-nato/",
  "author": "Dan Evon",
  "date": "16 July 2018"
}