{
  "vclaim_id": "vclaim-sno-woman-charged-eating-husband-alive",
  "vclaim": "An Ohio woman was charged by the Centerville Police Department with slowly eating her husband alive over a period of three years.",
  "title": "Was an Ohio Woman Charged After Slowly Eating Her Husband Alive?",
  "subtitle": "You won't be hearing about this grisly incident on the nightly news, for very good reason.",
  "page_url": "https://www.snopes.com/fact-check/woman-charged-eating-husband-alive/",
  "author": "David Emery",
  "date": "13 February 2019"
}