{
  "vclaim_id": "vclaim-sno-dmx-mopping-waffle-house",
  "vclaim": "Photographs show rapper and actor DMX mopping the floor at a Waffle House restaurant.",
  "title": "Do Photos Show DMX Mopping at Waffle House?",
  "subtitle": "The rapper reportedly once said, \"The minute you get too big to mop a floor or wipe a counter, that\u2019s the exact minute you have life f---ed up.\"",
  "page_url": "https://www.snopes.com/fact-check/dmx-mopping-waffle-house/",
  "author": "Bethania Palma",
  "date": "12 April 2021"
}