{
  "vclaim_id": "vclaim-sno-toronto-bar-cheer-kevin-durant-injury",
  "vclaim": "A video shows a crowd at a bar in Toronto erupting in applause as they watched NBA player Kevin Durant's 2019 playoff ending injury.",
  "title": "Did a Toronto Bar Cheer at Kevin Durant\u2019s Injury?",
  "subtitle": "Some fans really did cheer when Durant got injured, but this reaction video is digitally manipulated.",
  "page_url": "https://www.snopes.com/fact-check/toronto-bar-cheer-kevin-durant-injury/",
  "author": "Dan Evon",
  "date": "12 October 2021"
}