{
  "vclaim_id": "vclaim-sno-andrew-cuomo-dog-governors-mansion",
  "vclaim": "Disgraced former New York Gov. Andrew Cuomo left his dog, Captain, behind when he moved out of the governor\u2019s house in mid-August 2021, and asked if any staff member could keep him.",
  "title": "Did Andrew Cuomo Leave His Dog Behind in the Governor\u2019s Mansion?",
  "subtitle": "The disgraced former governor allegedly asked if any staff member could keep the dog.",
  "page_url": "https://www.snopes.com/fact-check/andrew-cuomo-dog-governors-mansion/",
  "author": "Nur Ibrahim",
  "date": "1 September 2021"
}