{
  "vclaim_id": "vclaim-sno-karolyi-illegal-immigrants",
  "vclaim": "U.S. Gymnastics coaches Bela and Marta Karolyi were illegal immigrants.",
  "title": "U.S. Gymnastics Coaches Bela and Marta Karolyi Were Illegal Immigrants?",
  "subtitle": "Rumor claims U.S. Gymnastics coaches Bela and Marta Karolyi were \"illegal immigrants\" to America, but historical accounts don't corroborate that descriptor.",
  "page_url": "https://www.snopes.com/fact-check/karolyi-illegal-immigrants/",
  "author": "Kim LaCapria",
  "date": "17 August 2016"
}